aiohttp_debugmode/__init__.py
aiohttp_debugmode/debug.py
aiohttp_debugmode/handler.py
aiohttp_debugmode/hlp.py
aiohttp_debugmode/manager.py
aiohttp_debugmode/observe_stdout.py
aiohttp_debugmode/pseudopty.py
aiohttp_debugmode-0.2.1.dist-info/LICENCE
aiohttp_debugmode-0.2.1.dist-info/METADATA
aiohttp_debugmode-0.2.1.dist-info/WHEEL
aiohttp_debugmode-0.2.1.dist-info/top_level.txt
aiohttp_debugmode-0.2.1.dist-info/RECORD
