Metadata-Version: 2.1
Name: aiohttp-debugmode
Version: 0.2.1
Summary: Run aiohttp server in subprocess ,automatically reload while dependencies/statics modified , debugtoolbar included. - GoodManWEN/aiohttp-debugmode
Home-page: https://github.com/GoodManWEN/aiohttp-debugmode
Author: WEN
License: UNKNOWN
Keywords: aiohttp,debug,aiohttp-debugmode,debugtoolbar
Platform: UNKNOWN
Classifier: Programming Language :: Python :: 3
Classifier: Programming Language :: Python :: 3.7
Classifier: Programming Language :: Python :: 3.8
Classifier: License :: OSI Approved :: MIT License
Classifier: Operating System :: POSIX :: Linux
Classifier: Operating System :: Microsoft :: Windows
Classifier: Framework :: AsyncIO
Requires-Python: >=3.7
Requires-Dist: aiohttp (>=3.4.0)
Requires-Dist: aiohttp-debugtoolbar (>=0.6.0)
Requires-Dist: watchdog (==0.10.2)
